Angua_Luggage/Angua.py
Angua_Luggage/AnguaUtils.py
Angua_Luggage/Luggage.py
Angua_Luggage/LuggageInterface.py
Angua_Luggage/__init__.py
Angua_Luggage/decorators.py
Angua_Luggage/exec_utils.py
Angua_Luggage/utils.py
Angua_Luggage/bin/ICTVEntrez.py
Angua_Luggage/bin/fetchSRA.py
Angua_Luggage/bin/getORFs.py
Angua_Luggage/bin/parseBlastMegan.py
Angua_Luggage/bin/parseBlastXML.py
Angua_Luggage/bin/spadesTidy.py
Angua_Luggage/bin/__pycache__/ICTVEntrez.cpython-310.pyc
Angua_Luggage/bin/__pycache__/fetchSRA.cpython-310.pyc
Angua_Luggage/bin/__pycache__/getORFs.cpython-310.pyc
Angua_Luggage/bin/__pycache__/parseBlastMegan.cpython-310.pyc
Angua_Luggage/bin/__pycache__/parseBlastXML.cpython-310.pyc
Angua_Luggage/bin/__pycache__/spadesTidy.cpython-310.pyc
Angua_Luggage/data/__init__.py
Angua_Luggage/data/annotatr_cli.r
Angua_Luggage/data/header.json
Angua_Luggage/data/logging.conf
Angua_Luggage/data/__pycache__/__init__.cpython-310.pyc
Angua_Luggage/test/__init__.py
Angua_Luggage/test/test_Luggage.py
Angua_Luggage/test/test_LuggageInterface.py
Angua_Luggage/test/test_parseBlastXML.py
Angua_Luggage-0.1.8.dist-info/LICENSE.txt
Angua_Luggage-0.1.8.dist-info/METADATA
Angua_Luggage-0.1.8.dist-info/WHEEL
Angua_Luggage-0.1.8.dist-info/entry_points.txt
Angua_Luggage-0.1.8.dist-info/top_level.txt
Angua_Luggage-0.1.8.dist-info/RECORD
